{
  "db_name": "PostgreSQL",
  "query": "\n            SELECT id, name, owner_id, file_type as \"file_type: _\", parent_folder_id, is_deleted, ttl\n            FROM files\n            WHERE LOWER(name) LIKE LOWER($1) AND is_deleted = FALSE\n            ",
  "describe": {
    "columns": [
      {
        "ordinal": 0,
        "name": "id",
        "type_info": "Uuid"
      },
      {
        "ordinal": 1,
        "name": "name",
        "type_info": "Text"
      },
      {
        "ordinal": 2,
        "name": "owner_id",
        "type_info": "Uuid"
      },
      {
        "ordinal": 3,
        "name": "file_type: _",
        "type_info": {
          "Custom": {
            "name": "file_type",
            "kind": {
              "Enum": [
                "Text",
                "Image",
                "Video",
                "Unknown"
              ]
            }
          }
        }
      },
      {
        "ordinal": 4,
        "name": "parent_folder_id",
        "type_info": "Uuid"
      },
      {
        "ordinal": 5,
        "name": "is_deleted",
        "type_info": "Bool"
      },
      {
        "ordinal": 6,
        "name": "ttl",
        "type_info": "Timestamptz"
      }
    ],
    "parameters": {
      "Left": [
        "Text"
      ]
    },
    "nullable": [
      false,
      false,
      false,
      false,
      false,
      false,
      true
    ]
  },
  "hash": "493e0bae24404630788c6dc477fb3aa562ae161d30b1bc3a4bb753bde48d8a66"
}
